cas_manifest/__init__.py
cas_manifest/ref.py
cas_manifest/registerable.py
cas_manifest/registry.py
cas_manifest/s3_hashfs.py
cas_manifest-0.4.1.dist-info/LICENSE
cas_manifest-0.4.1.dist-info/WHEEL
cas_manifest-0.4.1.dist-info/METADATA
cas_manifest-0.4.1.dist-info/RECORD
