Metadata-Version: 2.1
Name: cas-manifest
Version: 0.4.1
Summary: cas-manifest allows developers to store artifacts in a content-addressable store using a self-describing manifest
Home-page: https://github.com/danielhfrank/cas-manifest
License: MIT
Author: Dan Frank
Requires-Python: >=3.7,<4.0
Classifier: License :: OSI Approved :: MIT License
Classifier: Programming Language :: Python :: 3
Classifier: Programming Language :: Python :: 3.7
Classifier: Programming Language :: Python :: 3.8
Classifier: Programming Language :: Python :: 3.9
Requires-Dist: boto3 (>=1.9.201,<2.0.0)
Requires-Dist: hashfs (>=0.7.2,<0.8.0)
Requires-Dist: pydantic (>=1.6.1,<2.0.0)
Project-URL: Repository, https://github.com/danielhfrank/cas-manifest
